lambdata_austinwolff/__init__.py
lambdata_austinwolff/helper_function.py
Helper_Function-0.0.2.dist-info/METADATA
Helper_Function-0.0.2.dist-info/WHEEL
Helper_Function-0.0.2.dist-info/top_level.txt
Helper_Function-0.0.2.dist-info/RECORD
